budgetmanager/__init__.py
budgetmanager/admin.py
budgetmanager/apps.py
budgetmanager/metadata.py
budgetmanager/models.py
budgetmanager/pagination.py
budgetmanager/permissions.py
budgetmanager/serializers.py
budgetmanager/urls.py
budgetmanager/views.py
budgetmanager/migrations/0001_initial.py
budgetmanager/migrations/0002_budget_last_modified_budget_modified_by_and_more.py
budgetmanager/migrations/0003_sharecode.py
budgetmanager/migrations/__init__.py
budgetmanager-1.2.1.dist-info/LICENSE
budgetmanager-1.2.1.dist-info/METADATA
budgetmanager-1.2.1.dist-info/WHEEL
budgetmanager-1.2.1.dist-info/top_level.txt
budgetmanager-1.2.1.dist-info/RECORD
