Metadata-Version: 2.1
Name: budgetmanager
Version: 1.2.1
Summary: Django app for keeping track of budgets, payees, and payments
Author: Elli Greaves
License: BSD-3-Clause-Clear license
Project-URL: Homepage, https://github.com/Grvs44/budgetmanager
Classifier: Programming Language :: Python :: 3
Classifier: License :: OSI Approved :: BSD License
Classifier: Operating System :: OS Independent
Requires-Python: <4,>=3.10
License-File: LICENSE
Requires-Dist: django >=4.2.4
Requires-Dist: djangorestframework >=3.14.0
Requires-Dist: django-filter >=23.2
